OFE/OFE_Buttoms.py
OFE/OFE_Canvas.py
OFE/OFE_Field.py
OFE/OFE_Files.py
OFE/OFE_Graphics.py
OFE/OFE_Image.py
OFE/OFE_Panels.py
OFE/OFE_Status.py
OFE/OFE_main.py
OFE/__init__.py
OFE/fields.pak
OFE/title_logo.png
OFE/panels/Arrow_Down.png
OFE/panels/Arrow_Left.png
OFE/panels/Arrow_Right.png
OFE/panels/Arrow_Up.png
OFE/panels/Button_Arrow.png
OFE/panels/Button_ArrowDelete.png
OFE/panels/Button_ArrowLine.png
OFE/panels/Button_ArrowLineDelete.png
OFE/panels/Button_AutoBackTrack.png
OFE/panels/Button_Cancel.png
OFE/panels/Button_DeckPos.png
OFE/panels/Button_Delete.png
OFE/panels/Button_Mouse.png
OFE/panels/Button_OK.png
OFE/panels/Mouse_ArrowDelete.png
OFE/panels/Mouse_ArrowLine.png
OFE/panels/Mouse_ArrowLineDelete.png
OFE/panels/Mouse_Cancel.png
OFE/panels/Mouse_Mouse.png
OFE/panels/Mouse_OK.png
OFE/panels/Panel_Bonus.png
OFE/panels/Panel_Bonus_2.png
OFE/panels/Panel_Boss.png
OFE/panels/Panel_Boss_New.png
OFE/panels/Panel_Check.png
OFE/panels/Panel_Damage.png
OFE/panels/Panel_Damage_2.png
OFE/panels/Panel_Deck.png
OFE/panels/Panel_Draw.png
OFE/panels/Panel_Draw_2.png
OFE/panels/Panel_Drop.png
OFE/panels/Panel_Drop_2.png
OFE/panels/Panel_Encounter.png
OFE/panels/Panel_Encounter_2.png
OFE/panels/Panel_Heal.png
OFE/panels/Panel_Heal_2.png
OFE/panels/Panel_Ice.png
OFE/panels/Panel_Move.png
OFE/panels/Panel_Move_2.png
OFE/panels/Panel_Neutral.png
OFE/panels/Panel_Snow.png
OFE/panels/Panel_Void.png
OFE/panels/Panel_Warp.png
OFE/panels/Panel_WarpMove.png
OFE/panels/Panel_WarpMove_2.png
OFE/panels/Transform_AntiClock_test.png
OFE/panels/Transform_Cancel.png
OFE/panels/Transform_Clock_test.png
OFE/panels/Transform_Horizonal_test.png
OFE/panels/Transform_OK.png
OFE/panels/Transform_Vertical_test.png
OrangeFieldEditor-0.1.4.data/scripts/OFE.bat
OrangeFieldEditor-0.1.4.dist-info/METADATA
OrangeFieldEditor-0.1.4.dist-info/WHEEL
OrangeFieldEditor-0.1.4.dist-info/top_level.txt
OrangeFieldEditor-0.1.4.dist-info/RECORD
